{
  "psid": "15451338",
  "strong": [],
  "average": [],
  "weak": [
    {
      "subject": "physics",
      "chapter": "Units & Measurements",
      "percentage": 13.89
    },
    {
      "subject": "physics",
      "chapter": "Motion in a Straight Line",
      "percentage": 13.89
    },
    {
      "subject": "physics",
      "chapter": "Motion in a Plane",
      "percentage": 13.89
    },
    {
      "subject": "physics",
      "chapter": "Laws of Motion",
      "percentage": 13.89
    },
    {
      "subject": "physics",
      "chapter": "Work, Energy & Power",
      "percentage": 13.89
    },
    {
      "subject": "physics",
      "chapter": "System of Particles & Rotational Motion",
      "percentage": 13.89
    },
    {
      "subject": "chemistry",
      "chapter": "Some Basic Concepts of Chemistry",
      "percentage": 24.44
    },
    {
      "subject": "chemistry",
      "chapter": "Structure of Atom",
      "percentage": 24.44
    },
    {
      "subject": "chemistry",
      "chapter": "Classification of Elements and Periodicity in Properties",
      "percentage": 24.44
    },
    {
      "subject": "chemistry",
      "chapter": "Chemical Bonding and Molecular Structure",
      "percentage": 24.44
    },
    {
      "subject": "botany",
      "chapter": "The Living World",
      "percentage": 15.0
    },
    {
      "subject": "botany",
      "chapter": "Cell: The Unit of Life",
      "percentage": 15.0
    },
    {
      "subject": "botany",
      "chapter": "Cell Cycle & Cell Division",
      "percentage": 15.0
    },
    {
      "subject": "botany",
      "chapter": "Biological Classification",
      "percentage": 15.0
    },
    {
      "subject": "zoology",
      "chapter": "Structural Organisation in Animals- Animal Tissues",
      "percentage": 37.78
    },
    {
      "subject": "zoology",
      "chapter": "Biomolecules",
      "percentage": 37.78
    },
    {
      "subject": "zoology",
      "chapter": "Breathing & Exchange of Gases",
      "percentage": 37.78
    },
    {
      "subject": "zoology",
      "chapter": "Body Fluids & Circulation",
      "percentage": 37.78
    }
  ]
}