{
  "psid": "00015837374",
  "name": "Unknown",
  "batch": "RM06",
  "meta": {
    "tests_taken": 1,
    "latest_test_id": "AIATS1",
    "latest_test_order_idx": 7
  },
  "overall_performance": {
    "average_total_score": 203,
    "best_score": 203,
    "latest_score": 203,
    "consistency_index": 81.2,
    "trend": "stable"
  },
  "subjects": {
    "physics": {
      "average_percentage": 21,
      "strong_chapters": [],
      "average_chapters": [],
      "weak_chapters": [
        "Units & Measurements",
        "Motion in a Straight Line",
        "Motion in a Plane"
      ],
      "chapters": [
        {
          "name": "Units & Measurements",
          "rating": 2.1,
          "percentage": 21,
          "status": "Weak"
        },
        {
          "name": "Motion in a Straight Line",
          "rating": 2.1,
          "percentage": 21,
          "status": "Weak"
        },
        {
          "name": "Motion in a Plane",
          "rating": 2.1,
          "percentage": 21,
          "status": "Weak"
        }
      ]
    },
    "chemistry": {
      "average_percentage": 26,
      "strong_chapters": [],
      "average_chapters": [],
      "weak_chapters": [
        "Some Basic Concepts of Chemistry",
        "Structure of Atom"
      ],
      "chapters": [
        {
          "name": "Some Basic Concepts of Chemistry",
          "rating": 2.6,
          "percentage": 26,
          "status": "Weak"
        },
        {
          "name": "Structure of Atom",
          "rating": 2.6,
          "percentage": 26,
          "status": "Weak"
        }
      ]
    },
    "botany": {
      "average_percentage": 42,
      "strong_chapters": [],
      "average_chapters": [],
      "weak_chapters": [
        "Cell: The Unit of Life",
        "Cell Cycle and Cell Division",
        "The Living World"
      ],
      "chapters": [
        {
          "name": "Cell: The Unit of Life",
          "rating": 4.2,
          "percentage": 42,
          "status": "Weak"
        },
        {
          "name": "Cell Cycle and Cell Division",
          "rating": 4.2,
          "percentage": 42,
          "status": "Weak"
        },
        {
          "name": "The Living World",
          "rating": 4.2,
          "percentage": 42,
          "status": "Weak"
        }
      ]
    },
    "zoology": {
      "average_percentage": 25,
      "strong_chapters": [],
      "average_chapters": [],
      "weak_chapters": [
        "Structural Organisation in Animals- Animal Tissues",
        "Biomolecules"
      ],
      "chapters": [
        {
          "name": "Structural Organisation in Animals- Animal Tissues",
          "rating": 2.5,
          "percentage": 25,
          "status": "Weak"
        },
        {
          "name": "Biomolecules",
          "rating": 2.5,
          "percentage": 25,
          "status": "Weak"
        }
      ]
    }
  },
  "focus_insights": {
    "top_weak_chapters": [
      "Units & Measurements",
      "Motion in a Straight Line",
      "Motion in a Plane",
      "Some Basic Concepts of Chemistry",
      "Structure of Atom"
    ],
    "most_improved_chapters": [],
    "chapters_needing_attention": [
      "Units & Measurements",
      "Motion in a Straight Line",
      "Motion in a Plane",
      "Some Basic Concepts of Chemistry",
      "Structure of Atom",
      "Cell: The Unit of Life",
      "Cell Cycle and Cell Division",
      "The Living World",
      "Structural Organisation in Animals- Animal Tissues",
      "Biomolecules"
    ]
  },
  "tests": [
    {
      "test_id": "AIATS1",
      "norm_tid": "AIATS1",
      "syl_date": "2025-11-02T00:00:00",
      "order_idx": 7,
      "marks": {
        "physics": 37,
        "chemistry": 46,
        "botany": 75,
        "zoology": 45,
        "total": 203
      },
      "center_rank": 0,
      "air_rank": 0,
      "percentile": 28.19
    }
  ]
}