{
  "psid": "00006907002",
  "name": "Unknown",
  "batch": "RM05",
  "meta": {
    "tests_taken": 3,
    "latest_test_id": "AIATS2",
    "latest_test_order_idx": 11
  },
  "overall_performance": {
    "average_total_score": 535,
    "best_score": 548,
    "latest_score": 531,
    "consistency_index": 268.81,
    "trend": "improving"
  },
  "subjects": {
    "physics": {
      "average_percentage": 61,
      "strong_chapters": [],
      "average_chapters": [
        "Units & Measurements",
        "Motion in a Straight Line",
        "Motion in a Plane",
        "Laws of Motion",
        "Work, Energy and Power",
        "Moving Charges and Magnetism",
        "Magnetism and Matter",
        "Electromagnetic Induction",
        "Alternating Current"
      ],
      "weak_chapters": [],
      "chapters": [
        {
          "name": "Units & Measurements",
          "rating": 5.1,
          "percentage": 51,
          "status": "Average"
        },
        {
          "name": "Motion in a Straight Line",
          "rating": 5.1,
          "percentage": 51,
          "status": "Average"
        },
        {
          "name": "Motion in a Plane",
          "rating": 5.1,
          "percentage": 51,
          "status": "Average"
        },
        {
          "name": "Laws of Motion",
          "rating": 5.9,
          "percentage": 59,
          "status": "Average"
        },
        {
          "name": "Work, Energy and Power",
          "rating": 5.9,
          "percentage": 59,
          "status": "Average"
        },
        {
          "name": "Moving Charges and Magnetism",
          "rating": 6.9,
          "percentage": 69,
          "status": "Average"
        },
        {
          "name": "Magnetism and Matter",
          "rating": 6.9,
          "percentage": 69,
          "status": "Average"
        },
        {
          "name": "Electromagnetic Induction",
          "rating": 6.9,
          "percentage": 69,
          "status": "Average"
        },
        {
          "name": "Alternating Current",
          "rating": 6.9,
          "percentage": 69,
          "status": "Average"
        }
      ]
    },
    "chemistry": {
      "average_percentage": 77,
      "strong_chapters": [],
      "average_chapters": [
        "Some Basic Concepts of Chemistry",
        "Structure of Atom",
        "Classification of Elements and periodicity in properties",
        "chemical Bonding and molecular structure",
        "Hydrocarbons",
        "Haloalkanes and Haloarenes"
      ],
      "weak_chapters": [],
      "chapters": [
        {
          "name": "Classification of Elements and periodicity in properties",
          "rating": 7.2,
          "percentage": 72,
          "status": "Average"
        },
        {
          "name": "chemical Bonding and molecular structure",
          "rating": 7.2,
          "percentage": 72,
          "status": "Average"
        },
        {
          "name": "Hydrocarbons",
          "rating": 7.8,
          "percentage": 78,
          "status": "Average"
        },
        {
          "name": "Haloalkanes and Haloarenes",
          "rating": 7.8,
          "percentage": 78,
          "status": "Average"
        },
        {
          "name": "Some Basic Concepts of Chemistry",
          "rating": 7.9,
          "percentage": 79,
          "status": "Average"
        },
        {
          "name": "Structure of Atom",
          "rating": 7.9,
          "percentage": 79,
          "status": "Average"
        }
      ]
    },
    "botany": {
      "average_percentage": 79,
      "strong_chapters": [
        "Biological Classification",
        "Morphology of Flowering Plants"
      ],
      "average_chapters": [
        "Cell: The Unit of Life",
        "Cell Cycle and Cell Division",
        "The Living World",
        "Plant Growth and Development",
        "Sexual Reproduction in Flowering Plants"
      ],
      "weak_chapters": [],
      "chapters": [
        {
          "name": "Cell: The Unit of Life",
          "rating": 7.8,
          "percentage": 78,
          "status": "Average"
        },
        {
          "name": "Cell Cycle and Cell Division",
          "rating": 7.8,
          "percentage": 78,
          "status": "Average"
        },
        {
          "name": "The Living World",
          "rating": 7.8,
          "percentage": 78,
          "status": "Average"
        },
        {
          "name": "Plant Growth and Development",
          "rating": 7.8,
          "percentage": 78,
          "status": "Average"
        },
        {
          "name": "Sexual Reproduction in Flowering Plants",
          "rating": 7.8,
          "percentage": 78,
          "status": "Average"
        },
        {
          "name": "Biological Classification",
          "rating": 8.1,
          "percentage": 81,
          "status": "Mastered"
        },
        {
          "name": "Morphology of Flowering Plants",
          "rating": 8.1,
          "percentage": 81,
          "status": "Mastered"
        }
      ]
    },
    "zoology": {
      "average_percentage": 82,
      "strong_chapters": [
        "Structural Organisation in Animals- Animal Tissues",
        "Biomolecules",
        "Breathing & Exchange of Gases",
        "Body Fluids & Circulation"
      ],
      "average_chapters": [
        "Animal Kingdom-II: Chordates",
        "Structural Organisation in Animals- Animal Morphology (Cockroach & Frog)"
      ],
      "weak_chapters": [],
      "chapters": [
        {
          "name": "Animal Kingdom-II: Chordates",
          "rating": 7.9,
          "percentage": 79,
          "status": "Average"
        },
        {
          "name": "Structural Organisation in Animals- Animal Morphology (Cockroach & Frog)",
          "rating": 7.9,
          "percentage": 79,
          "status": "Average"
        },
        {
          "name": "Breathing & Exchange of Gases",
          "rating": 8.3,
          "percentage": 83,
          "status": "Mastered"
        },
        {
          "name": "Body Fluids & Circulation",
          "rating": 8.3,
          "percentage": 83,
          "status": "Mastered"
        },
        {
          "name": "Structural Organisation in Animals- Animal Tissues",
          "rating": 8.4,
          "percentage": 84,
          "status": "Mastered"
        },
        {
          "name": "Biomolecules",
          "rating": 8.4,
          "percentage": 84,
          "status": "Mastered"
        }
      ]
    }
  },
  "focus_insights": {
    "top_weak_chapters": [],
    "most_improved_chapters": [],
    "chapters_needing_attention": []
  },
  "tests": [
    {
      "test_id": "AIATS1",
      "norm_tid": "AIATS1",
      "syl_date": "2025-11-02T00:00:00",
      "order_idx": 7,
      "marks": {
        "physics": 91,
        "chemistry": 143,
        "botany": 140,
        "zoology": 151,
        "total": 525
      },
      "center_rank": 0,
      "air_rank": 0,
      "percentile": 72.92
    },
    {
      "test_id": "AIATS2",
      "norm_tid": "AIATS2",
      "syl_date": "2025-11-30T00:00:00",
      "order_idx": 11,
      "marks": {
        "physics": 106,
        "chemistry": 130,
        "botany": 145,
        "zoology": 150,
        "total": 531
      },
      "center_rank": 131,
      "air_rank": 0,
      "percentile": 9341.0
    },
    {
      "test_id": "AIATS3",
      "norm_tid": "AIATS3",
      "syl_date": "2025-12-31T00:00:00",
      "order_idx": 13,
      "marks": {
        "physics": 125,
        "chemistry": 141,
        "botany": 140,
        "zoology": 142,
        "total": 548
      },
      "center_rank": 65,
      "air_rank": 0,
      "percentile": 76.11
    }
  ]
}