{
  "psid": "00015141719",
  "name": "Unknown",
  "meta": {
    "tests_taken": 9,
    "first_test_date": "02-11-2025",
    "latest_test_date": "31-12-2025"
  },
  "overall_performance": {
    "average_total_score": 355,
    "best_score": 425,
    "latest_score": 425,
    "consistency_index": 0.4363,
    "trend": "improving"
  },
  "subjects": {
    "physics": {
      "average_percentage": 18,
      "trend": "stable",
      "strong_chapters": [],
      "average_chapters": [],
      "weak_chapters": [
        "Laws of Motion",
        "Work, Energy and Power",
        "Units & Measurements",
        "Motion in a Straight Line",
        "Motion in a Plane",
        "Thermal Properties of Matter",
        "Thermodynamics",
        "Kinetic Theory",
        "Oscillations",
        "Waves",
        "Electric Charges & Fields",
        "Electrostatic Potential and Capacitance",
        "Current Electricity",
        "System of Particles and Rotational Motion",
        "Gravitation",
        "Mechanical Properties of Solids",
        "Mechanical Properties of Fluids",
        "Work, Energy & Power",
        "System of Particles & Rotational Motion"
      ]
    },
    "chemistry": {
      "average_percentage": 42,
      "trend": "improving",
      "strong_chapters": [],
      "average_chapters": [
        "Chemical Kinetics",
        "Organic Chemistry: Some Basic Principles & Techniques",
        "Chemical Bonding and Molecular Structure"
      ],
      "weak_chapters": [
        "Classification of Elements and periodicity in properties",
        "chemical Bonding and molecular structure",
        "Some Basic Concepts of Chemistry",
        "Structure of Atom",
        "Equilibrium",
        "Redox Reactions",
        "Electrochemistry",
        "Solutions",
        "Thermodynamics"
      ]
    },
    "botany": {
      "average_percentage": 61,
      "trend": "stable",
      "strong_chapters": [
        "Morphology of Flowering Plants"
      ],
      "average_chapters": [
        "Biological Classification",
        "Cell: The Unit of Life",
        "Cell Cycle and Cell Division",
        "The Living World",
        "Anatomy of Flowering Plants",
        "Plant Kingdom"
      ],
      "weak_chapters": [
        "Photosynthesis in Higher Plants",
        "Respiration in Plants"
      ]
    },
    "zoology": {
      "average_percentage": 65,
      "trend": "declining",
      "strong_chapters": [
        "Neural Control & Coordination",
        "Locomotion & Movement"
      ],
      "average_chapters": [
        "Breathing & Exchange of Gases",
        "Body Fluids & Circulation",
        "Locomotion & Movement-II: (Upto muscle and bone disorders)",
        "Chemical Coordination & Integration",
        "Animal Kingdom-I: General accounts & Non-chordates",
        "Excretory Products & their Elimination",
        "Breathing & Exchange of Gases-I: (upto mechanism of breathing)",
        "Locomotion & Movement-I: (Upto properties of muscle contraction)"
      ],
      "weak_chapters": [
        "Structural Organisation in Animals- Animal Tissues",
        "Biomolecules"
      ]
    }
  },
  "focus_insights": {
    "top_weak_chapters": [
      "Oscillations",
      "Waves",
      "Electric Charges & Fields",
      "Laws of Motion",
      "Work, Energy and Power"
    ],
    "most_improved_chapters": [
      "Oscillations",
      "Waves",
      "Electric Charges & Fields",
      "Chemical Coordination & Integration",
      "Excretory Products & their Elimination"
    ],
    "chapters_needing_attention": [
      "Oscillations",
      "Waves",
      "Electric Charges & Fields",
      "Laws of Motion",
      "Work, Energy and Power",
      "Units & Measurements",
      "Motion in a Straight Line",
      "Motion in a Plane",
      "System of Particles and Rotational Motion",
      "Gravitation",
      "Mechanical Properties of Solids",
      "Mechanical Properties of Fluids",
      "Electrostatic Potential and Capacitance",
      "Current Electricity",
      "Thermal Properties of Matter",
      "Thermodynamics",
      "Kinetic Theory",
      "Some Basic Concepts of Chemistry",
      "Structure of Atom",
      "Work, Energy & Power",
      "System of Particles & Rotational Motion",
      "Solutions",
      "Structural Organisation in Animals- Animal Tissues",
      "Biomolecules",
      "Redox Reactions",
      "Electrochemistry",
      "Classification of Elements and periodicity in properties",
      "chemical Bonding and molecular structure",
      "Photosynthesis in Higher Plants",
      "Respiration in Plants",
      "Thermodynamics",
      "Equilibrium"
    ]
  },
  "disclaimer": "Chapter-wise performance is estimated based on an equal distribution of subject marks across the test syllabus. This data is for analytical purposes and may not reflect specific question-level weighting."
}