{
  "graphs": [
    {
      "graph_id": "all_tests_subject_trend",
      "title": "Overall Subject Performance (All Tests)",
      "x_axis": {
        "label": "Test Date",
        "values": [
          "1900-01-01",
          "2025-07-02",
          "2025-07-23",
          "2025-08-20",
          "2025-08-27",
          "2025-10-01",
          "2025-11-02",
          "2025-11-05",
          "2025-11-12",
          "2025-11-26",
          "2025-11-30",
          "2025-12-28",
          "2025-12-31"
        ]
      },
      "datasets": [
        {
          "subject": "physics",
          "data": [
            131,
            110,
            131,
            126,
            111,
            108,
            108,
            123,
            153,
            120,
            108,
            107,
            110
          ]
        },
        {
          "subject": "chemistry",
          "data": [
            126,
            95,
            121,
            165,
            160,
            140,
            80,
            124,
            102,
            80,
            140,
            92,
            95
          ]
        },
        {
          "subject": "botany",
          "data": [
            123,
            151,
            165,
            165,
            155,
            145,
            125,
            140,
            145,
            127,
            125,
            140,
            141
          ]
        },
        {
          "subject": "zoology",
          "data": [
            170,
            160,
            150,
            175,
            165,
            160,
            145,
            145,
            155,
            155,
            165,
            110,
            160
          ]
        }
      ]
    },
    {
      "graph_id": "aiats_subject_trend",
      "title": "AIATS Subject Performance",
      "x_axis": {
        "label": "Test Date",
        "values": [
          "2025-11-02",
          "2025-11-30",
          "2025-12-31"
        ]
      },
      "datasets": [
        {
          "subject": "physics",
          "data": [
            108,
            108,
            110
          ]
        },
        {
          "subject": "chemistry",
          "data": [
            80,
            140,
            95
          ]
        },
        {
          "subject": "botany",
          "data": [
            125,
            125,
            141
          ]
        },
        {
          "subject": "zoology",
          "data": [
            145,
            165,
            160
          ]
        }
      ]
    },
    {
      "graph_id": "ft_subject_trend",
      "title": "Fortnightly Test (FT) Subject Performance",
      "x_axis": {
        "label": "Test Date",
        "values": [
          "1900-01-01",
          "2025-07-02",
          "2025-07-23",
          "2025-08-20",
          "2025-10-01",
          "2025-11-05",
          "2025-11-26",
          "2025-12-28"
        ]
      },
      "datasets": [
        {
          "subject": "physics",
          "data": [
            131,
            110,
            131,
            126,
            108,
            123,
            120,
            107
          ]
        },
        {
          "subject": "chemistry",
          "data": [
            126,
            95,
            121,
            165,
            140,
            124,
            80,
            92
          ]
        },
        {
          "subject": "botany",
          "data": [
            123,
            151,
            165,
            165,
            145,
            140,
            127,
            140
          ]
        },
        {
          "subject": "zoology",
          "data": [
            170,
            160,
            150,
            175,
            160,
            145,
            155,
            110
          ]
        }
      ]
    },
    {
      "graph_id": "nbts_subject_trend",
      "title": "NCERT Booster Test (NBTS) Subject Performance",
      "x_axis": {
        "label": "Test Date",
        "values": [
          "2025-08-27",
          "2025-11-12"
        ]
      },
      "datasets": [
        {
          "subject": "physics",
          "data": [
            111,
            153
          ]
        },
        {
          "subject": "chemistry",
          "data": [
            160,
            102
          ]
        },
        {
          "subject": "botany",
          "data": [
            155,
            145
          ]
        },
        {
          "subject": "zoology",
          "data": [
            165,
            155
          ]
        }
      ]
    }
  ]
}