{
  "psid": "00015535394",
  "name": "Unknown",
  "batch": "RM04",
  "meta": {
    "tests_taken": 3,
    "latest_test_id": "AIATS2",
    "latest_test_order_idx": 11
  },
  "overall_performance": {
    "average_total_score": 262,
    "best_score": 290,
    "latest_score": 290,
    "consistency_index": 119.83,
    "trend": "declining"
  },
  "subjects": {
    "physics": {
      "average_percentage": 12,
      "strong_chapters": [],
      "average_chapters": [],
      "weak_chapters": [
        "Units & Measurements",
        "Motion in a Straight Line",
        "Motion in a Plane",
        "Laws of Motion",
        "Work, Energy and Power",
        "Moving Charges and Magnetism",
        "Magnetism and Matter",
        "Electromagnetic Induction",
        "Alternating Current"
      ],
      "chapters": [
        {
          "name": "Moving Charges and Magnetism",
          "rating": 0.6,
          "percentage": 6,
          "status": "Weak"
        },
        {
          "name": "Magnetism and Matter",
          "rating": 0.6,
          "percentage": 6,
          "status": "Weak"
        },
        {
          "name": "Electromagnetic Induction",
          "rating": 0.6,
          "percentage": 6,
          "status": "Weak"
        },
        {
          "name": "Alternating Current",
          "rating": 0.6,
          "percentage": 6,
          "status": "Weak"
        },
        {
          "name": "Laws of Motion",
          "rating": 1.2,
          "percentage": 12,
          "status": "Weak"
        },
        {
          "name": "Work, Energy and Power",
          "rating": 1.2,
          "percentage": 12,
          "status": "Weak"
        },
        {
          "name": "Units & Measurements",
          "rating": 2.1,
          "percentage": 21,
          "status": "Weak"
        },
        {
          "name": "Motion in a Straight Line",
          "rating": 2.1,
          "percentage": 21,
          "status": "Weak"
        },
        {
          "name": "Motion in a Plane",
          "rating": 2.1,
          "percentage": 21,
          "status": "Weak"
        }
      ]
    },
    "chemistry": {
      "average_percentage": 29,
      "strong_chapters": [],
      "average_chapters": [],
      "weak_chapters": [
        "Some Basic Concepts of Chemistry",
        "Structure of Atom",
        "Classification of Elements and periodicity in properties",
        "chemical Bonding and molecular structure",
        "Hydrocarbons",
        "Haloalkanes and Haloarenes"
      ],
      "chapters": [
        {
          "name": "Hydrocarbons",
          "rating": 1.7,
          "percentage": 17,
          "status": "Weak"
        },
        {
          "name": "Haloalkanes and Haloarenes",
          "rating": 1.7,
          "percentage": 17,
          "status": "Weak"
        },
        {
          "name": "Some Basic Concepts of Chemistry",
          "rating": 2.8,
          "percentage": 28,
          "status": "Weak"
        },
        {
          "name": "Structure of Atom",
          "rating": 2.8,
          "percentage": 28,
          "status": "Weak"
        },
        {
          "name": "Classification of Elements and periodicity in properties",
          "rating": 4.1,
          "percentage": 41,
          "status": "Weak"
        },
        {
          "name": "chemical Bonding and molecular structure",
          "rating": 4.1,
          "percentage": 41,
          "status": "Weak"
        }
      ]
    },
    "botany": {
      "average_percentage": 45,
      "strong_chapters": [],
      "average_chapters": [
        "Cell: The Unit of Life",
        "Cell Cycle and Cell Division",
        "The Living World"
      ],
      "weak_chapters": [
        "Biological Classification",
        "Morphology of Flowering Plants",
        "Plant Growth and Development",
        "Sexual Reproduction in Flowering Plants"
      ],
      "chapters": [
        {
          "name": "Plant Growth and Development",
          "rating": 3.4,
          "percentage": 34,
          "status": "Weak"
        },
        {
          "name": "Sexual Reproduction in Flowering Plants",
          "rating": 3.4,
          "percentage": 34,
          "status": "Weak"
        },
        {
          "name": "Biological Classification",
          "rating": 4.3,
          "percentage": 43,
          "status": "Weak"
        },
        {
          "name": "Morphology of Flowering Plants",
          "rating": 4.3,
          "percentage": 43,
          "status": "Weak"
        },
        {
          "name": "Cell: The Unit of Life",
          "rating": 5.4,
          "percentage": 54,
          "status": "Average"
        },
        {
          "name": "Cell Cycle and Cell Division",
          "rating": 5.4,
          "percentage": 54,
          "status": "Average"
        },
        {
          "name": "The Living World",
          "rating": 5.4,
          "percentage": 54,
          "status": "Average"
        }
      ]
    },
    "zoology": {
      "average_percentage": 61,
      "strong_chapters": [],
      "average_chapters": [
        "Structural Organisation in Animals- Animal Tissues",
        "Biomolecules",
        "Breathing & Exchange of Gases",
        "Body Fluids & Circulation",
        "Animal Kingdom-II: Chordates",
        "Structural Organisation in Animals- Animal Morphology (Cockroach & Frog)"
      ],
      "weak_chapters": [],
      "chapters": [
        {
          "name": "Structural Organisation in Animals- Animal Tissues",
          "rating": 5.2,
          "percentage": 52,
          "status": "Average"
        },
        {
          "name": "Biomolecules",
          "rating": 5.2,
          "percentage": 52,
          "status": "Average"
        },
        {
          "name": "Animal Kingdom-II: Chordates",
          "rating": 6.4,
          "percentage": 64,
          "status": "Average"
        },
        {
          "name": "Structural Organisation in Animals- Animal Morphology (Cockroach & Frog)",
          "rating": 6.4,
          "percentage": 64,
          "status": "Average"
        },
        {
          "name": "Breathing & Exchange of Gases",
          "rating": 6.5,
          "percentage": 65,
          "status": "Average"
        },
        {
          "name": "Body Fluids & Circulation",
          "rating": 6.5,
          "percentage": 65,
          "status": "Average"
        }
      ]
    }
  },
  "focus_insights": {
    "top_weak_chapters": [
      "Units & Measurements",
      "Motion in a Straight Line",
      "Motion in a Plane",
      "Laws of Motion",
      "Work, Energy and Power"
    ],
    "most_improved_chapters": [],
    "chapters_needing_attention": [
      "Units & Measurements",
      "Motion in a Straight Line",
      "Motion in a Plane",
      "Laws of Motion",
      "Work, Energy and Power",
      "Moving Charges and Magnetism",
      "Magnetism and Matter",
      "Electromagnetic Induction",
      "Alternating Current",
      "Some Basic Concepts of Chemistry",
      "Structure of Atom",
      "Classification of Elements and periodicity in properties",
      "chemical Bonding and molecular structure",
      "Hydrocarbons",
      "Haloalkanes and Haloarenes",
      "Biological Classification",
      "Morphology of Flowering Plants",
      "Plant Growth and Development",
      "Sexual Reproduction in Flowering Plants"
    ]
  },
  "tests": [
    {
      "test_id": "AIATS1",
      "norm_tid": "AIATS1",
      "syl_date": "2025-11-02T00:00:00",
      "order_idx": 7,
      "marks": {
        "physics": 37,
        "chemistry": 51,
        "botany": 97,
        "zoology": 94,
        "total": 279
      },
      "center_rank": 0,
      "air_rank": 0,
      "percentile": 38.75
    },
    {
      "test_id": "AIATS2",
      "norm_tid": "AIATS2",
      "syl_date": "2025-11-30T00:00:00",
      "order_idx": 11,
      "marks": {
        "physics": 21,
        "chemistry": 74,
        "botany": 78,
        "zoology": 117,
        "total": 290
      },
      "center_rank": 643,
      "air_rank": 0,
      "percentile": 42628.0
    },
    {
      "test_id": "AIATS3",
      "norm_tid": "AIATS3",
      "syl_date": "2025-12-31T00:00:00",
      "order_idx": 13,
      "marks": {
        "physics": 10,
        "chemistry": 30,
        "botany": 62,
        "zoology": 116,
        "total": 218
      },
      "center_rank": 673,
      "air_rank": 0,
      "percentile": 30.28
    }
  ]
}