{
  "psid": "15716524",
  "strong": [],
  "average": [],
  "weak": [
    {
      "subject": "physics",
      "chapter": "Moving Charges and Magnetism",
      "percentage": 9.44
    },
    {
      "subject": "physics",
      "chapter": "Magnetism and Matter",
      "percentage": 9.44
    },
    {
      "subject": "physics",
      "chapter": "Electromagnetic Induction",
      "percentage": 9.44
    },
    {
      "subject": "physics",
      "chapter": "Alternating Current",
      "percentage": 9.44
    },
    {
      "subject": "chemistry",
      "chapter": "Hydrocarbons",
      "percentage": 17.22
    },
    {
      "subject": "chemistry",
      "chapter": "Haloalkanes and Haloarenes",
      "percentage": 17.22
    },
    {
      "subject": "botany",
      "chapter": "Plant Growth and Development",
      "percentage": 19.44
    },
    {
      "subject": "botany",
      "chapter": "Sexual Reproduction in Flowering Plants",
      "percentage": 19.44
    },
    {
      "subject": "zoology",
      "chapter": "Animal Kingdom-II: Chordates",
      "percentage": 26.67
    },
    {
      "subject": "zoology",
      "chapter": "Structural Organisation in Animals- Animal Morphology (Cockroach & Frog)",
      "percentage": 26.67
    }
  ]
}