{
  "graphs": [
    {
      "graph_id": "all_tests_subject_trend",
      "title": "Overall Subject Performance (All Tests)",
      "x_axis": {
        "label": "Test Date",
        "values": [
          "2025-08-20",
          "2025-08-27",
          "2025-11-02",
          "2025-11-30",
          "2025-12-31"
        ]
      },
      "datasets": [
        {
          "subject": "physics",
          "data": [
            79,
            71,
            27,
            28,
            54
          ]
        },
        {
          "subject": "chemistry",
          "data": [
            101,
            116,
            65,
            95,
            38
          ]
        },
        {
          "subject": "botany",
          "data": [
            120,
            136,
            76,
            123,
            121
          ]
        },
        {
          "subject": "zoology",
          "data": [
            136,
            116,
            67,
            96,
            59
          ]
        }
      ]
    },
    {
      "graph_id": "aiats_subject_trend",
      "title": "AIATS Subject Performance",
      "x_axis": {
        "label": "Test Date",
        "values": [
          "2025-11-02",
          "2025-11-30",
          "2025-12-31"
        ]
      },
      "datasets": [
        {
          "subject": "physics",
          "data": [
            27,
            28,
            54
          ]
        },
        {
          "subject": "chemistry",
          "data": [
            65,
            95,
            38
          ]
        },
        {
          "subject": "botany",
          "data": [
            76,
            123,
            121
          ]
        },
        {
          "subject": "zoology",
          "data": [
            67,
            96,
            59
          ]
        }
      ]
    },
    {
      "graph_id": "ft_subject_trend",
      "title": "Fortnightly Test (FT) Subject Performance",
      "x_axis": {
        "label": "Test Date",
        "values": [
          "2025-08-20"
        ]
      },
      "datasets": [
        {
          "subject": "physics",
          "data": [
            79
          ]
        },
        {
          "subject": "chemistry",
          "data": [
            101
          ]
        },
        {
          "subject": "botany",
          "data": [
            120
          ]
        },
        {
          "subject": "zoology",
          "data": [
            136
          ]
        }
      ]
    },
    {
      "graph_id": "nbts_subject_trend",
      "title": "NCERT Booster Test (NBTS) Subject Performance",
      "x_axis": {
        "label": "Test Date",
        "values": [
          "2025-08-27"
        ]
      },
      "datasets": [
        {
          "subject": "physics",
          "data": [
            71
          ]
        },
        {
          "subject": "chemistry",
          "data": [
            116
          ]
        },
        {
          "subject": "botany",
          "data": [
            136
          ]
        },
        {
          "subject": "zoology",
          "data": [
            116
          ]
        }
      ]
    }
  ]
}