{
  "psid": "00017954747",
  "strong": [
    {
      "subject": "zoology",
      "chapter": "Structural Organisation in Animals- Animal Tissues",
      "percentage": 81.11
    },
    {
      "subject": "zoology",
      "chapter": "Biomolecules",
      "percentage": 81.11
    }
  ],
  "average": [
    {
      "subject": "botany",
      "chapter": "Cell: The Unit of Life",
      "percentage": 70.0
    },
    {
      "subject": "botany",
      "chapter": "Cell Cycle and Cell Division",
      "percentage": 70.0
    },
    {
      "subject": "botany",
      "chapter": "The Living World",
      "percentage": 70.0
    }
  ],
  "weak": [
    {
      "subject": "physics",
      "chapter": "Units & Measurements",
      "percentage": 37.22
    },
    {
      "subject": "physics",
      "chapter": "Motion in a Straight Line",
      "percentage": 37.22
    },
    {
      "subject": "physics",
      "chapter": "Motion in a Plane",
      "percentage": 37.22
    },
    {
      "subject": "chemistry",
      "chapter": "Some Basic Concepts of Chemistry",
      "percentage": 37.22
    },
    {
      "subject": "chemistry",
      "chapter": "Structure of Atom",
      "percentage": 37.22
    }
  ]
}