{
  "psid": "00015748372",
  "strong": [
    {
      "subject": "zoology",
      "chapter": "Animal Kingdom-II: Chordates",
      "percentage": 78.33
    },
    {
      "subject": "zoology",
      "chapter": "Structural Organisation in Animals- Animal Morphology (Cockroach & Frog)",
      "percentage": 78.33
    }
  ],
  "average": [
    {
      "subject": "physics",
      "chapter": "Moving Charges and Magnetism",
      "percentage": 57.22
    },
    {
      "subject": "physics",
      "chapter": "Magnetism and Matter",
      "percentage": 57.22
    },
    {
      "subject": "physics",
      "chapter": "Electromagnetic Induction",
      "percentage": 57.22
    },
    {
      "subject": "physics",
      "chapter": "Alternating Current",
      "percentage": 57.22
    },
    {
      "subject": "chemistry",
      "chapter": "Hydrocarbons",
      "percentage": 60.0
    },
    {
      "subject": "chemistry",
      "chapter": "Haloalkanes and Haloarenes",
      "percentage": 60.0
    },
    {
      "subject": "botany",
      "chapter": "Plant Growth and Development",
      "percentage": 72.78
    },
    {
      "subject": "botany",
      "chapter": "Sexual Reproduction in Flowering Plants",
      "percentage": 72.78
    }
  ],
  "weak": []
}